uniparser_meadow_mari/__init__.py
uniparser_meadow_mari/data_nodiacritics/__init__.py
uniparser_meadow_mari/data_nodiacritics/bad_analyses.txt
uniparser_meadow_mari/data_nodiacritics/lex_rules.txt
uniparser_meadow_mari/data_nodiacritics/lexemes.txt
uniparser_meadow_mari/data_nodiacritics/meadow_mari_disambiguation.cg3
uniparser_meadow_mari/data_nodiacritics/paradigms.txt
uniparser_meadow_mari/data_strict/__init__.py
uniparser_meadow_mari/data_strict/bad_analyses.txt
uniparser_meadow_mari/data_strict/lex_rules.txt
uniparser_meadow_mari/data_strict/lexemes.txt
uniparser_meadow_mari/data_strict/meadow_mari_disambiguation.cg3
uniparser_meadow_mari/data_strict/paradigms.txt
uniparser_meadow_mari-1.1.18.dist-info/licenses/LICENSE
uniparser_meadow_mari-1.1.18.dist-info/METADATA
uniparser_meadow_mari-1.1.18.dist-info/WHEEL
uniparser_meadow_mari-1.1.18.dist-info/top_level.txt
uniparser_meadow_mari-1.1.18.dist-info/RECORD
