Metadata-Version: 2.4
Name: uniparser-meadow-mari
Version: 1.1.18
Summary: Rule-based morphological analysis for Meadow Mari
Home-page: https://github.com/timarkh/uniparser-grammar-meadow-mari
Author: Timofey Arkhangelskiy
Author-email: timarkh@gmail.com
Project-URL: Bug Tracker, https://github.com/timarkh/uniparser-grammar-meadow-mari/issues
Classifier: Programming Language :: Python :: 3
Classifier: License :: OSI Approved :: MIT License
Classifier: Operating System :: OS Independent
Classifier: Intended Audience :: Science/Research
Classifier: Topic :: Text Processing :: Linguistic
Requires-Python: >=3.7
License-File: LICENSE
Requires-Dist: uniparser-morph>=2.2.0
Requires-Dist: importlib-resources
Dynamic: license-file
